[
"metadata", 
{
"dc:language": "no", 
"ncc:charset": "utf-8", 
"dc:title": "Jamen, Benny", 
"ncc:tocItems": "5", 
"dc:publisher": "NLB", 
"ncc:footnotes": "0", 
"ncc:sidebars": "0", 
"ncc:generator": "EasePublisher 2.13 Build 163 # 044FS5213089123", 
"ncc:prodNotes": "0", 
"dc:identifier": "613757", 
"dc:format": "Daisy 2.02", 
"dc:date": "2008-11-10", 
"ncc:maxPageNormal": "0", 
"ncc:kByteSize": "6659", 
"ncc:pageNormal": "0", 
"prod:last_used_id": "", 
"ncc:depth": "1", 
"ncc:totalTime": "00:04:33", 
"ncc:narrator": "Arnhild Littlere", 
"ncc:pageSpecial": "0", 
"ncc:files": "43", 
"dc:creator": "Lindgren, Barbro", 
"ncc:pageFront": "0", 
"ncc:setInfo": "1 of 1", 
"prod:ep_update": ""
}
]